src/__init__.py
src/server.py
src/model/__init__.py
src/model/request/__init__.py
src/model/request/wikipedia_search.py
src/model/response/__init__.py
src/model/response/wikipedia_detail.py
src/model/response/wikipedia_search_result.py
src/request/__init__.py
src/request/wikipedia_search.py
src/response/__init__.py
src/response/wikipedia_detail.py
src/response/wikipedia_search_result.py
wiki_mcp_server-0.0.6.dist-info/METADATA
wiki_mcp_server-0.0.6.dist-info/WHEEL
wiki_mcp_server-0.0.6.dist-info/entry_points.txt
wiki_mcp_server-0.0.6.dist-info/RECORD
