Metadata-Version: 2.4
Name: wiki-mcp-server
Version: 0.0.6
Summary: 내 MCP 서버
Author-email: hero <icraft2170@gmail.com>
License: MIT
Requires-Python: >=3.10
Requires-Dist: beautifulsoup4>=4.12.0
Requires-Dist: mcp[cli]>=1.6.0
